binpi/__init__.py
binpi/deserializer.py
binpi/into_type_instance.py
binpi/list.py
binpi/plans.py
binpi/reader.py
binpi/serializer.py
binpi/types.py
binpi/utils.py
binpi/writer.py
binpi-0.1.21.dist-info/licenses/LICENSE
tests/__init__.py
tests/serialize_test.py
tests/shared.py
binpi-0.1.21.dist-info/METADATA
binpi-0.1.21.dist-info/WHEEL
binpi-0.1.21.dist-info/top_level.txt
binpi-0.1.21.dist-info/RECORD
