Metadata-Version: 2.4
Name: binpi
Version: 0.1.21
Summary: Simple library for de/serializing binary data
Home-page: https://github.com/romansvozil/binpi
Author: Roman Svozil
License: MIT
License-File: LICENSE
Dynamic: author
Dynamic: description
Dynamic: description-content-type
Dynamic: home-page
Dynamic: license
Dynamic: license-file
Dynamic: summary
